MapAvro/__init__.py
MapAvro/avroConverter.py
MapAvro/utils/__init__.py
MapAvro/utils/maps.py
MapAvro/utils/utils.py
mapavro-0.1.6.dist-info/LICENSE
mapavro-0.1.6.dist-info/METADATA
mapavro-0.1.6.dist-info/WHEEL
mapavro-0.1.6.dist-info/top_level.txt
mapavro-0.1.6.dist-info/RECORD
