Metadata-Version: 2.2
Name: MapAvro
Version: 0.1.6
Summary: A package for converting Bengali text to Avro and vice versa.
Author: Shahriar Kabir Nahin
License: MIT License
Project-URL: Homepage, https://github.com/SKNahin/MapAvro
Project-URL: Bug Tracker, https://github.com/SKNahin/MapAvro/issues
Project-URL: Documentation, https://github.com/SKNahin/MapAvro/blob/main/README.md
Keywords: Bengali,Avro,Romanized Bengali,Bengali Romanization,Bangla
Classifier: Programming Language :: Python :: 3
Classifier: License :: OSI Approved :: MIT License
Classifier: Operating System :: OS Independent
Classifier: Natural Language :: English
Classifier: Topic :: Scientific/Engineering :: Artificial Intelligence
Classifier: Intended Audience :: Developers
Classifier: Intended Audience :: Science/Research
Requires-Python: >=3.8
License-File: LICENSE
Requires-Dist: bnunicodenormalizer
